samanage/__init__.py
samanage-1.0.dist-info/DESCRIPTION.rst
samanage-1.0.dist-info/METADATA
samanage-1.0.dist-info/RECORD
samanage-1.0.dist-info/WHEEL
samanage-1.0.dist-info/metadata.json
samanage-1.0.dist-info/top_level.txt
