Metadata-Version: 2.0
Name: samanage
Version: 1.0
Summary: Library to interface with samanage
Home-page: https://github.com/b4ldr/samanage
Author: John Bond
Author-email: pypi@johnbond.org
License: BSD
Platform: UNKNOWN
